{
    "CompleterNpc": "Orc chief",
    "NextQuestId": -1,
    "RandomReward": 0b,
    "QuestRepeat": 0,
    "QuestCompletion": 0,
    "IgnoreNBT": 0b,
    "Title": "34. Odyssea",
    "Text": "I managed to escape the captivity. Now I have to get to the Orc chief and give him the message.",
    "QuestFactionPoints": {
        "DecreaseFaction1Points": 0b,
        "OptionFaction2Points": 100,
        "OptionFactions1": 7,
        "OptionFactions2": -1,
        "OptionFaction1Points": 300,
        "DecreaseFaction2Points": 0b
    },
    "RewardExp": 0,
    "QuestCommand": "",
    "ModRev": 18,
    "Type": 0,
    "QuestMail": {
        "Sender": "",
        "BeenRead": 0b,
        "Message": {
        },
        "MailItems": [
        ],
        "MailQuest": -1,
        "TimePast": 1591531682127L,
        "Time": 0L,
        "Subject": ""
    },
    "IgnoreDamage": 0b,
    "Rewards": {
        "NpcMiscInv": [
        ]
    },
    "Items": {
        "NpcMiscInv": [
            {
                "Slot": 0b,
                "ForgeCaps": {
                    "customnpcs:itemscripteddata": {
                    }
                },
                "id": "minecraft:written_book",
                "Count": 1b,
                "tag": {
                    "pages": [
                        "{\"text\":\"Their encampment is located somewhere to the north of that Hobbit village.\\n\\nWe will send more info when we know more.\\n\\nOar-Thul\"}"
                    ],
                    "author": "Unknown",
                    "title": "Position",
                    "resolved": 1b
                },
                "Damage": 0s
            }
        ]
    },
    "LeaveItems": 0b,
    "CompleteText": "Done.",
    "NextQuestTitle": ""
}
