{
    "CompleterNpc": "Lovec",
    "NextQuestId": -1,
    "RandomReward": 0b,
    "QuestRepeat": 0,
    "QuestCompletion": 0,
    "IgnoreNBT": 0b,
    "Title": "1. Kdo jsem a kde jsem",
    "Text": "Nejsem zrovna ve sve kuzi.
Probral jsem se v hostinci a nemam tuseni kdo, nebo kde vlastne jsem.
Hospodsky mi rekl, ze me zachranil mistni lovec. A onen zmineny lovec je primo zde v hostinci.

Mel bych si s nim promluvit",
    "QuestFactionPoints": {
        "DecreaseFaction1Points": 0b,
        "OptionFaction2Points": 100,
        "OptionFactions1": 2,
        "OptionFactions2": -1,
        "OptionFaction1Points": 10,
        "DecreaseFaction2Points": 0b
    },
    "RewardExp": 0,
    "QuestCommand": "",
    "ModRev": 18,
    "Type": 0,
    "QuestMail": {
        "Sender": "",
        "BeenRead": 0b,
        "Message": {
        },
        "MailItems": [
        ],
        "MailQuest": -1,
        "TimePast": 1554907947329L,
        "Time": 0L,
        "Subject": ""
    },
    "IgnoreDamage": 0b,
    "Rewards": {
        "NpcMiscInv": [
        ]
    },
    "Items": {
        "NpcMiscInv": [
        ]
    },
    "LeaveItems": 0b,
    "CompleteText": "Uspesne jsem nasel Lovce!",
    "NextQuestTitle": ""
}
