{"stat.flyOneCm":276721,"stat.pickup.minecraft.double_plant":1,"stat.drop.minecraft.sign":1,"stat.walkOneCm":127682,"stat.drop":2,"stat.pickup.minecraft.wheat_seeds":7,"stat.pickup.minecraft.brown_mushroom":2,"stat.jump":181,"stat.swimOneCm":33184,"stat.playOneMinute":53296,"stat.climbOneCm":6725,"stat.pickup.minecraft.torch":1,"stat.leaveGame":1,"stat.sneakTime":2443,"stat.crouchOneCm":9810,"stat.drop.minecraft.dirt":1,"stat.timeSinceDeath":53296,"stat.pickup.minecraft.sapling":3,"stat.sprintOneCm":104415,"stat.useItem.minecraft.stone_slab2":238,"stat.diveOneCm":58717,"stat.useItem.minecraft.water_bucket":1558,"stat.useItem.minecraft.glowstone":1}